gimdl.py
gimdl-0.0.14.dist-info/LICENSE
gimdl-0.0.14.dist-info/METADATA
gimdl-0.0.14.dist-info/WHEEL
gimdl-0.0.14.dist-info/top_level.txt
gimdl-0.0.14.dist-info/RECORD
