Metadata-Version: 2.1
Name: gimdl
Version: 0.0.14
Summary: Google Image Search Downloader - using API 
Home-page: UNKNOWN
License: UNKNOWN
Project-URL: GitHub, https://github.com/RGGH/gimdl
Keywords: googleimages,images,search
Platform: UNKNOWN
Classifier: Development Status :: 3 - Alpha
Classifier: License :: OSI Approved :: MIT License
Classifier: Programming Language :: Python :: 3.6
Classifier: Programming Language :: Python :: 3.7
Classifier: Programming Language :: Python :: 3.8
Classifier: Programming Language :: Python :: 3.9
Classifier: Operating System :: OS Independent
